pkrhistorytransfer/__init__.py
pkrhistorytransfer/app.py
pkrhistorytransfer/daily_upload.py
pkrhistorytransfer/frequent_upload.py
pkrhistorytransfer/loader.py
pkrhistorytransfer-1.0.0.dist-info/METADATA
pkrhistorytransfer-1.0.0.dist-info/WHEEL
pkrhistorytransfer-1.0.0.dist-info/top_level.txt
pkrhistorytransfer-1.0.0.dist-info/RECORD
