Metadata-Version: 2.1
Name: pkrhistorytransfer
Version: 1.0.0
Summary: A Poker Package to transfer poker history files in a dedicated directory
Home-page: https://github.com/manggy94/PokerHistoryLocalTransfer
Author: Alexandre MANGWA
Author-email: alex.mangwa@gmail.com
License: UNKNOWN
Keywords: poker pkrhistory history pkr pkrhistorytransfer pokerhistory transfer downloader
Platform: UNKNOWN
Classifier: Development Status :: 4 - Beta
Classifier: Intended Audience :: Developers
Classifier: License :: OSI Approved :: MIT License
Classifier: Natural Language :: English
Classifier: Natural Language :: French
Classifier: Programming Language :: Python
Classifier: Programming Language :: Python :: 3
Classifier: Topic :: Games/Entertainment
Classifier: Topic :: Games/Entertainment :: Board Games
Requires-Dist: boto3
Requires-Dist: python-dotenv
